corona_python/__init__.py
corona_python/country.py
corona_python/world.py
corona_python-1.0.1.dist-info/LICENSE
corona_python-1.0.1.dist-info/METADATA
corona_python-1.0.1.dist-info/WHEEL
corona_python-1.0.1.dist-info/top_level.txt
corona_python-1.0.1.dist-info/RECORD
