Metadata-Version: 2.1
Name: corona-python
Version: 1.0.1
Summary: A Python 3 wrapper for the COVID-19 API
Home-page: https://github.com/MakufonSkifto/corona-python
Author: MakufonSkifto
Author-email: emirsurmen@gmail.com
License: MIT
Platform: UNKNOWN
Classifier: Programming Language :: Python :: 3
Classifier: License :: OSI Approved :: MIT License
Requires-Python: >=3.6
Requires-Dist: requests
